README.md
setup.py
fwl_ddd_seedwork/__init__.py
fwl_ddd_seedwork.egg-info/PKG-INFO
fwl_ddd_seedwork.egg-info/SOURCES.txt
fwl_ddd_seedwork.egg-info/dependency_links.txt
fwl_ddd_seedwork.egg-info/top_level.txt
fwl_ddd_seedwork/domain/DomainExceptions.py
fwl_ddd_seedwork/domain/Entity.py
fwl_ddd_seedwork/domain/ValidationRule.py
fwl_ddd_seedwork/domain/ValueObject.py
fwl_ddd_seedwork/domain/__init__.py
fwl_ddd_seedwork/dto/DTO.py
fwl_ddd_seedwork/dto/__init__.py
fwl_ddd_seedwork/infrastructure/Exceptions.py
fwl_ddd_seedwork/infrastructure/Schema.py
fwl_ddd_seedwork/infrastructure/__init__.py
fwl_ddd_seedwork/mapper/BaseMapper.py
fwl_ddd_seedwork/mapper/__init__.py