Metadata-Version: 1.2
Name: fwl-ddd-seedwork
Version: 0.6
Summary: simple ddd seedwork
Home-page: https://github.com/aherculano/fwl-ddd-seedwork
Author: Alexandre Herculano
Author-email: aherculano0109@gmail.com
License: MIT
Platform: UNKNOWN
Requires-Python: >=3.6
